{
	"allItems": "All Groups",
	"allItemsTabCount": "1,505",
	"directoryObject": "groups",
	"directoryTitle": "Groups Directory",
	"directoryUrl": "https://commons.gc.cuny.edu/groups/",
	"myItems": "My Groups",
	"myItemsTabCount": "123",
	"dropOpts": {
		"campus": [
			{ "name": "Baruch College", "value": "0" },
			{ "name": "Borough of Manhattan Community College", "value": "1" },
			{ "name": "Bronx Community College", "value": "2" },
			{ "name": "Brooklyn College", "value": "3" },
			{ "name": "CUNY Central", "value": "4" },
			{ "name": "CUNY Graduate Center", "value": "5" },
			{ "name": "CUNY Graduate School of Public Health and Health Policy", "value": "6" },
			{ "name": "CUNY School of Labor and Urban Studies", "value": "7" },
			{ "name": "CUNY School of Law", "value": "8" },
			{ "name": "CUNY School of Medicine", "value": "9" },
			{ "name": "CUNY School of Professional Studies", "value": "10" },
			{ "name": "City College of New York", "value": "11" },
			{ "name": "College of Staten Island", "value": "12" },
			{ "name": "Craig Newmark Graduate School of Journalism", "value": "13" },
			{ "name": "Guttman Community College", "value": "14" },
			{ "name": "Hostos Community College", "value": "15" },
			{ "name": "Hunter College", "value": "16" },
			{ "name": "John Jay College of Criminal Justice", "value": "17" },
			{ "name": "Kingsborough Community College", "value": "18" },
			{ "name": "LaGuardia Community College", "value": "19" },
			{ "name": "Lehman College", "value": "20" },
			{ "name": "Macaulay Honors College", "value": "21" },
			{ "name": "Medgar Evers College", "value": "22" },
			{ "name": "New York City College of Technology", "value": "23" },
			{ "name": "Queens College", "value": "24" },
			{ "name": "Queensborough Community College", "value": "25" }
		],
		"purpose": [
			{ "name": "Committee", "value": "committee" },
			{ "name": "Community of Interest", "value": "community-of-interest" },
			{ "name": "Conference", "value": "conference" },
			{ "name": "Department/Program/Center", "value": "department-program-center" },
			{ "name": "Other", "value": "other" },
			{ "name": "Personal", "value": "personal" },
			{ "name": "Portfolio", "value": "portfolio" },
			{ "name": "Project", "value": "project" },
			{ "name": "Publication", "value": "publication" },
			{ "name": "Teaching", "value": "teaching" },
			{ "name": "Working Group", "value": "working-group" }
		]
	}
}
